{"id":"b8e32zij9egyzswosocp3t8","title":"Pytorch","desc":"","updated":1660318545151,"created":1660318545151,"custom":{},"fname":"programming-languages.python.Pytorch","type":"note","vault":{"fsPath":".","selfContained":true,"name":"knowledge"},"contentHash":"7b503aa555c4bc3a072c49b9cf080f06","links":[{"from":{"fname":"programming-languages.python","vaultName":"knowledge"},"type":"backlink","position":{"start":{"line":21,"column":136,"offset":914},"end":{"line":21,"column":176,"offset":954},"indent":[]},"value":"programming-languages.python.Pytorch","alias":"programming-languages.python.Pytorch"}],"anchors":{},"children":[],"parent":"i7qra5ip0gwchs30f5at7rx","data":{}}
