{"id":"dftloyxhwpi83dg622hxnw6","title":"Gevent","desc":"","updated":1660792904046,"created":1660790599082,"custom":{},"fname":"programming-languages.python.gevent","type":"note","vault":{"fsPath":".","selfContained":true,"name":"knowledge"},"contentHash":"aa36320591723966c7a9661ed7cbc60b","links":[{"from":{"fname":"programming-languages.python","vaultName":"knowledge"},"type":"backlink","position":{"start":{"line":56,"column":3,"offset":2056},"end":{"line":56,"column":42,"offset":2095},"indent":[]},"value":"programming-languages.python.gevent","alias":"programming-languages.python.gevent"}],"anchors":{"介绍":{"type":"header","text":"介绍","value":"介绍","line":7,"column":0,"depth":2},"应用":{"type":"header","text":"应用","value":"应用","line":27,"column":0,"depth":2}},"children":[],"parent":"i7qra5ip0gwchs30f5at7rx","data":{}}
